README.md
setup.py
investor8_sdk/__init__.py
investor8_sdk/api_client.py
investor8_sdk/configuration.py
investor8_sdk/rest.py
investor8_sdk.egg-info/PKG-INFO
investor8_sdk.egg-info/SOURCES.txt
investor8_sdk.egg-info/dependency_links.txt
investor8_sdk.egg-info/requires.txt
investor8_sdk.egg-info/top_level.txt
investor8_sdk/api/__init__.py
investor8_sdk/api/earnings_api.py
investor8_sdk/api/email_api.py
investor8_sdk/api/financials_api.py
investor8_sdk/api/metrics_api.py
investor8_sdk/api/news_api.py
investor8_sdk/api/price_api.py
investor8_sdk/api/screener_api.py
investor8_sdk/api/search_api.py
investor8_sdk/api/settings_api.py
investor8_sdk/api/stock_info_api.py
investor8_sdk/api/tags_api.py
investor8_sdk/api/user_api.py
investor8_sdk/models/__init__.py
investor8_sdk/models/active_company_dto.py
investor8_sdk/models/add_to_watchlist_dto.py
investor8_sdk/models/authentication_request.py
investor8_sdk/models/authentication_source.py
investor8_sdk/models/authorize_account_request_dto.py
investor8_sdk/models/authorize_account_response_dto.py
investor8_sdk/models/change_password_dto.py
investor8_sdk/models/company_info_dto.py
investor8_sdk/models/create_auth_req_dto.py
investor8_sdk/models/create_plot_dto.py
investor8_sdk/models/create_screen_dto.py
investor8_sdk/models/create_update_news.py
investor8_sdk/models/create_user_dto.py
investor8_sdk/models/create_user_res_dto.py
investor8_sdk/models/create_watchlist_dto.py
investor8_sdk/models/current_metadat_metrics_dto.py
investor8_sdk/models/current_metrics_dto.py
investor8_sdk/models/current_momentum_metrics_dto.py
investor8_sdk/models/daily_metrics_dto.py
investor8_sdk/models/detailed_latest_price_dto.py
investor8_sdk/models/discovery_source.py
investor8_sdk/models/earning_metrics_dto.py
investor8_sdk/models/email_type.py
investor8_sdk/models/financial_metric_metadata_dto.py
investor8_sdk/models/financial_report_dto.py
investor8_sdk/models/financial_tag.py
investor8_sdk/models/financials_growth.py
investor8_sdk/models/get_list_metric_views_dto.py
investor8_sdk/models/get_list_metrics_description_dto.py
investor8_sdk/models/get_list_metrics_metadata_dto.py
