Metadata-Version: 2.1
Name: investor8-sdk
Version: 1.1.108
Summary: Investoreight Core API
Home-page: UNKNOWN
Author-email: info@investoreight.com
License: UNKNOWN
Project-URL: Homepage, https://www.investoreight.com/
Project-URL: Documentation, https://github.com/investoreight/investor8-sdk#readme
Project-URL: Download, https://github.com/investoreight/investor8-sdk/releases
Project-URL: Source Code, https://github.com/investoreight/investor8-sdk
Project-URL: Bug Tracker, https://github.com/investoreight/investor8-sdk/issues
Keywords: Swagger,Investoreight Core API
Platform: UNKNOWN
